terminal_agent_x/__init__.py
terminal_agent_x/tax.py
terminal_agent_x-0.1.10.dist-info/LICENSE
terminal_agent_x-0.1.10.dist-info/METADATA
terminal_agent_x-0.1.10.dist-info/WHEEL
terminal_agent_x-0.1.10.dist-info/entry_points.txt
terminal_agent_x-0.1.10.dist-info/top_level.txt
terminal_agent_x-0.1.10.dist-info/RECORD
