Metadata-Version: 2.1
Name: terminal-agent-x
Version: 0.1.10
Summary: A terminal agent for terminal users.
Author-email: LyuLumos <lyujiuyang0@gmail.com>
Project-URL: Homepage, https://github.com/LyuLumos/Terminal-Agent-X
Project-URL: Bug Tracker, https://github.com/LyuLumos/Terminal-Agent-X/issues
Classifier: License :: OSI Approved :: GNU General Public License v3 (GPLv3)
Classifier: Programming Language :: Python :: 3
Classifier: Programming Language :: Python :: 3.6
Classifier: Programming Language :: Python :: 3.7
Classifier: Programming Language :: Python :: 3.8
Classifier: Programming Language :: Python :: 3.9
Classifier: Programming Language :: Python :: 3.10
Classifier: Programming Language :: Python :: 3.11
Requires-Python: >=3.6
License-File: LICENSE
Requires-Dist: psutil
